{
  "version": 1,
  "updatedAt": "2026-04-13T21:36:29.748Z",
  "entries": {
    "memory:memory/2026-04-10.md:21:48": {
      "key": "memory:memory/2026-04-10.md:21:48",
      "path": "memory/2026-04-10.md",
      "startLine": 21,
      "endLine": 48,
      "source": "memory",
      "snippet": "- No TODOs/FIXMEs in codebase - Recent features completed: browser analytics, menu OCR integration, geolocation tracking, QR Studio Current feature inventory: - QR Types: URL, Text, Email, Phone, SMS, Location, vCard, MeCard, WiFi, Event - Analytics: Timeline, OS breakdown, Browser breakdown (new), Country/City geo data, Referrers - Customization: Templates, colors, patterns (dot type, corner type) - Export: PDF generation, QR code download - Advanced: Batch generation, QR Studio, Menu OCR, folder/tag organization - Infrastructure: Supabase auth, cloud storage, abuse detection, geolocation tracking Potential enhancement areas identified: 1. QR code scanning mobile experience (currently lim",
      "recallCount": 1,
      "dailyCount": 0,
      "totalScore": 0.4948303759098053,
      "maxScore": 0.4948303759098053,
      "firstRecalledAt": "2026-04-12T09:25:04.014Z",
      "lastRecalledAt": "2026-04-12T09:25:04.014Z",
      "queryHashes": [
        "63fa4c644cfb"
      ],
      "recallDays": [
        "2026-04-12"
      ],
      "conceptTags": [
        "todos/fixmes",
        "country/city",
        "folder/tag",
        "todos",
        "fixmes",
        "codebase",
        "recent",
        "features"
      ]
    },
    "memory:memory/2026-04-07.md:1:1": {
      "key": "memory:memory/2026-04-07.md:1:1",
      "path": "memory/2026-04-07.md",
      "startLine": 1,
      "endLine": 1,
      "source": "memory",
      "snippet": "[proactive] Mode A — Enhanced quickqr dashboard with analytics visualization (scan timeline, OS breakdown, recent activity) — tests pass, committed ddd4f1a",
      "recallCount": 11,
      "dailyCount": 0,
      "totalScore": 5.405938409268856,
      "maxScore": 0.539948084950447,
      "firstRecalledAt": "2026-04-12T12:24:21.673Z",
      "lastRecalledAt": "2026-04-13T21:36:29.748Z",
      "queryHashes": [
        "b07f12a6add5",
        "fe5cb06d605f",
        "bb123ea1ea13",
        "8dd441ee806b",
        "cb008b82fca9",
        "337145283dc1",
        "9f34b595f62a",
        "5acaf49c25a3",
        "2685bde948f3",
        "e131e5c848e2",
        "63448d2bed55"
      ],
      "recallDays": [
        "2026-04-12",
        "2026-04-13"
      ],
      "conceptTags": [
        "proactive",
        "mode",
        "enhanced",
        "quickqr",
        "dashboard",
        "analytics",
        "visualization",
        "scan"
      ]
    },
    "memory:memory/2026-04-11.md:1:2": {
      "key": "memory:memory/2026-04-11.md:1:2",
      "path": "memory/2026-04-11.md",
      "startLine": 1,
      "endLine": 2,
      "source": "memory",
      "snippet": "[proactive] Mode B — Scanned QuickQR project for pending work — Found UTM Templates and Analytics CSV Export already implemented, pixel integration completed earlier today. Posted status to dev channel.",
      "recallCount": 11,
      "dailyCount": 0,
      "totalScore": 5.465520244836807,
      "maxScore": 0.5254934400320053,
      "firstRecalledAt": "2026-04-12T12:24:21.673Z",
      "lastRecalledAt": "2026-04-13T21:36:29.748Z",
      "queryHashes": [
        "b07f12a6add5",
        "fe5cb06d605f",
        "bb123ea1ea13",
        "8dd441ee806b",
        "cb008b82fca9",
        "337145283dc1",
        "9f34b595f62a",
        "5acaf49c25a3",
        "2685bde948f3",
        "e131e5c848e2",
        "63448d2bed55"
      ],
      "recallDays": [
        "2026-04-12",
        "2026-04-13"
      ],
      "conceptTags": [
        "proactive",
        "mode",
        "scanned",
        "quickqr",
        "project",
        "pending",
        "found",
        "utm"
      ]
    },
    "memory:memory/2026-04-12.md:1:4": {
      "key": "memory:memory/2026-04-12.md:1:4",
      "path": "memory/2026-04-12.md",
      "startLine": 1,
      "endLine": 4,
      "source": "memory",
      "snippet": "--- [proactive] Mode A — Checked QuickQR project status. Found that CSV export feature in AnalyticsDashboard.tsx was already implemented. Attempted to add component tests but environment is Node (no DOM). Removed failing test file. Service tests pass (108 tests). Updated .gitignore to exclude .openclaw/ directory. Strike counter at 0.",
      "recallCount": 8,
      "dailyCount": 0,
      "totalScore": 3.9011767804622646,
      "maxScore": 0.5034172296524048,
      "firstRecalledAt": "2026-04-12T12:24:21.673Z",
      "lastRecalledAt": "2026-04-13T03:23:55.080Z",
      "queryHashes": [
        "b07f12a6add5",
        "fe5cb06d605f",
        "bb123ea1ea13",
        "8dd441ee806b",
        "cb008b82fca9",
        "337145283dc1",
        "9f34b595f62a",
        "5acaf49c25a3"
      ],
      "recallDays": [
        "2026-04-12"
      ],
      "conceptTags": [
        "analyticsdashboard.tsx",
        "proactive",
        "mode",
        "checked",
        "quickqr",
        "project",
        "status",
        "found"
      ]
    },
    "memory:memory/2026-04-13.md:1:7": {
      "key": "memory:memory/2026-04-13.md:1:7",
      "path": "memory/2026-04-13.md",
      "startLine": 1,
      "endLine": 7,
      "source": "memory",
      "snippet": "[proactive] Mode A — Added folderService with 38 integration tests — commit from earlier run [proactive] Mode A — Added 14 unit tests for imageProxy utility functions (proxifyImageUrl, validateImageUrl, preloadImage) with comprehensive coverage for CORS proxy handling, image validation, and preloading. [proactive] Mode A — Added database migration for utm_templates table — enables UTM template feature with RLS policies, commit 23fdd7a [proactive] Mode A — Added PixelManager component with 8 integration tests for marketing pixel integration — supports Facebook Pixel, Google Ads, LinkedIn Insight Tag with form validation — commit a661cb8 [proactive] Mode A — Fixed TypeScript errors in 3 QR com",
      "recallCount": 3,
      "dailyCount": 0,
      "totalScore": 1.443034717440605,
      "maxScore": 0.5063107579946518,
      "firstRecalledAt": "2026-04-13T19:36:18.709Z",
      "lastRecalledAt": "2026-04-13T21:36:29.748Z",
      "queryHashes": [
        "2685bde948f3",
        "e131e5c848e2",
        "63448d2bed55"
      ],
      "recallDays": [
        "2026-04-13"
      ],
      "conceptTags": [
        "utm-templates",
        "proactive",
        "mode",
        "added",
        "folderservice",
        "integration",
        "tests",
        "commit"
      ]
    },
    "memory:memory/2026-04-12.md:1:2": {
      "key": "memory:memory/2026-04-12.md:1:2",
      "path": "memory/2026-04-12.md",
      "startLine": 1,
      "endLine": 2,
      "source": "memory",
      "snippet": "[proactive] Mode A — Added authService integration tests — 16 tests covering all 6 auth functions (register, login, loginWithGoogle, logout, getCurrentUser, getSession) plus comprehensive error handling — commit c44688b",
      "recallCount": 3,
      "dailyCount": 0,
      "totalScore": 1.310795897245407,
      "maxScore": 0.4543923050165176,
      "firstRecalledAt": "2026-04-13T19:36:18.709Z",
      "lastRecalledAt": "2026-04-13T21:36:29.748Z",
      "queryHashes": [
        "2685bde948f3",
        "e131e5c848e2",
        "63448d2bed55"
      ],
      "recallDays": [
        "2026-04-13"
      ],
      "conceptTags": [
        "proactive",
        "mode",
        "added",
        "authservice",
        "integration",
        "tests",
        "covering",
        "all"
      ]
    }
  }
}
